tkquick/__init__.py
tkquick/app/__init__.py
tkquick/gui/__init__.py
tkquick/gui/batteries.py
tkquick/gui/maker.py
tkquick/gui/plastik_theme.py
tkquick/gui/style_defaults.py
tkquick/gui/tkquick_base.py
tkquick/gui/tools.py
tkquick/gui/tooltip.py
tkquick-0.1.3.dist-info/DESCRIPTION.rst
tkquick-0.1.3.dist-info/METADATA
tkquick-0.1.3.dist-info/RECORD
tkquick-0.1.3.dist-info/WHEEL
tkquick-0.1.3.dist-info/metadata.json
tkquick-0.1.3.dist-info/pbr.json
tkquick-0.1.3.dist-info/top_level.txt
