Metadata-Version: 2.0
Name: tkquick
Version: 0.1.3
Summary: Collection of tools for building Gui Desktop Applications with tkinter
Home-page: https://github.com/timeyyy/tkquick
Author: timeyyy
Author-email: tim_eichler@hotmail.com
License: BSD3
Keywords: tkinter gui build rapid cookbook
Platform: UNKNOWN
Classifier: Development Status :: 3 - Alpha
Classifier: Intended Audience :: Developers
Classifier: Topic :: Software Development :: Build Tools
Classifier: License :: OSI Approved :: BSD License
Classifier: Programming Language :: Python :: 3
Classifier: Programming Language :: Python :: 3.2
Classifier: Programming Language :: Python :: 3.3
Classifier: Programming Language :: Python :: 3.4
Requires-Dist: Pillow
